azure_blob_processor/__init__.py
azure_blob_processor/decompressor.py
azure_blob_processor-0.3.2.dist-info/LICENSE.txt
azure_blob_processor-0.3.2.dist-info/METADATA
azure_blob_processor-0.3.2.dist-info/WHEEL
azure_blob_processor-0.3.2.dist-info/top_level.txt
azure_blob_processor-0.3.2.dist-info/RECORD
