Metadata-Version: 2.1
Name: azure-blob-processor
Version: 0.3.2
Summary: Library to process file in Azure blob storage
Home-page: https://github.com/zhenbzha/azure-blob-processor
Author: Zhenbo Zhang
Author-email: zhenbo.zhang@outlook.com
License: MIT
Download-URL: https://github.com/zhenbzha/azure-blob-processor
Keywords: Azure,blob
Platform: UNKNOWN
Classifier: Development Status :: 3 - Alpha
Classifier: Intended Audience :: Developers
Classifier: Topic :: Software Development :: Build Tools
Classifier: License :: OSI Approved :: MIT License
Classifier: Programming Language :: Python :: 3
Classifier: Programming Language :: Python :: 3.4
Classifier: Programming Language :: Python :: 3.5
Classifier: Programming Language :: Python :: 3.6
Requires-Dist: aiofile (==3.5.0)
Requires-Dist: aiohttp (==3.7.4.post0)
Requires-Dist: azure-eventhub (==5.5.0)
Requires-Dist: azure-storage-blob (==12.8.1)
